neuralplot.py
neuralplot-0.0.8.dist-info/LICENSE
neuralplot-0.0.8.dist-info/METADATA
neuralplot-0.0.8.dist-info/WHEEL
neuralplot-0.0.8.dist-info/top_level.txt
neuralplot-0.0.8.dist-info/RECORD
