Metadata-Version: 2.1
Name: neuralplot
Version: 0.0.8
Summary: A Library for visualizing Neural Networks.
Home-page: https://github.com/Rajsoni03/neuralplot
Author: Rajkumar Soni
Author-email: rajksoni029@gmail.com
License: UNKNOWN
Platform: UNKNOWN
Classifier: Programming Language :: Python :: 3
Classifier: License :: OSI Approved :: MIT License
Classifier: Operating System :: OS Independent
Requires-Dist: matplotlib (>=3.1numpy>=1.16)
